textnorm/__init__.py
textnorm-1.2.dist-info/LICENSE.txt
textnorm-1.2.dist-info/METADATA
textnorm-1.2.dist-info/WHEEL
textnorm-1.2.dist-info/top_level.txt
textnorm-1.2.dist-info/RECORD
