Metadata-Version: 2.1
Name: textnorm
Version: 1.2
Summary: A simple package for normalizing whitespace and Unicode composition forms in Python 3 strings
Home-page: https://github.com/isawnyu/textnorm
Author: Tom Elliott
Author-email: tom.elliott@nyu.edu
License: LICENSE.txt
Keywords: "text normalization","whitespace normalization","unicode normalization"
Platform: UNKNOWN
Classifier: Development Status :: 5 - Production/Stable
Classifier: Intended Audience :: Developers
Classifier: Topic :: Text Processing :: General
Classifier: License :: OSI Approved :: GNU Affero General Public License v3
Classifier: Programming Language :: Python :: 3.8
Classifier: Programming Language :: Python :: 3 :: Only
